{
  "cssTheme": "Obsidian gruvbox",
  "enabledCssSnippets": [
    "General Tweaks",
    "custom-callouts",
    "colored-bookmarks",
    "Colored Sidebar Items",
    "checkbox",
    "Notebook Backgrounds",
    "extended-colorschemes",
    "Daily Note Themes",
    "wider-tables"
  ],
  "showViewHeader": true,
  "showRibbon": false,
  "theme": "obsidian",
  "accentColor": "",
  "interfaceFontFamily": "",
  "textFontFamily": "",
  "monospaceFontFamily": "",
  "translucency": false,
  "baseFontSizeAction": false,
  "baseFontSize": 20
}